pinger/__init__.py
pinger/app/__init__.py
pinger/app/secrets/__init__.py
pinger/app/struct/__init__.py
pinger/cli/__init__.py
pinger/cli/app/cd/struct/__init__.py
pinger/cli/app/env/struct/__init__.py
pinger/cli/app/scale/struct/__init__.py
pinger/cli/app/secrets/struct/__init__.py
pinger/cli/app/struct/__init__.py
pinger/cli/infra/struct/__init__.py
pinger/config/__init__.py
pinger/config/struct/__init__.py
pinger/infra/__init__.py
pinger/infra/struct/__init__.py
pinger/secrets/__init__.py
pinger/secrets/struct/__init__.py
pinger_cli-0.1.98.dist-info/LICENSE
pinger_cli-0.1.98.dist-info/METADATA
pinger_cli-0.1.98.dist-info/WHEEL
pinger_cli-0.1.98.dist-info/entry_points.txt
pinger_cli-0.1.98.dist-info/RECORD
