Metadata-Version: 2.3
Name: pinger-cli
Version: 0.1.98
Summary: pinger
License: MIT
Keywords: pinger,platform,engineering
Author: engineering
Author-email: engineering@pinger.com
Requires-Python: >=3.9,<4.0
Classifier: License :: OSI Approved :: MIT License
Classifier: Programming Language :: Python :: 3
Classifier: Programming Language :: Python :: 3.9
Classifier: Programming Language :: Python :: 3.10
Classifier: Programming Language :: Python :: 3.11
Classifier: Programming Language :: Python :: 3.12
Classifier: Programming Language :: Python :: 3.13
Requires-Dist: boto3 (>=1.37.33,<2.0.0)
Requires-Dist: build (>=1.2.2.post1,<2.0.0)
Requires-Dist: homebrew-pypi-poet (>=0.10.0,<0.11.0)
Requires-Dist: pydantic (>=2.11.2,<3.0.0)
Requires-Dist: pyyaml (>=6.0.2,<7.0.0)
Requires-Dist: twine (>=6.1.0,<7.0.0)
Requires-Dist: typer (>=0.15.2,<0.16.0)
Project-URL: Homepage, https://github.com/drzln/pinger
Project-URL: Repository, https://github.com/drzln/pinger
